chordnet/__init__.py
chordnet/_net.py
chordnet/_node.py
chordnet/address.py
chordnet/chordnet.py
chordnet/py.typed
chordnet-2.2.2.dist-info/licenses/LICENSE
chordnet-2.2.2.dist-info/WHEEL
chordnet-2.2.2.dist-info/METADATA
chordnet-2.2.2.dist-info/RECORD
