Metadata-Version: 2.4
Name: chordnet
Version: 2.2.2
Summary: Implementation of the chord peer-to-peer networking protocol, introduced by Stoica et al.
Keywords: Chord,Chord protocol,distributed systems,peer-to-peer,P2P,hash table,lookup,scalability,Python,networking,decentralized,routing,overlay network,distributed hash table,DHT
Author: Jack Lowrie
License-Expression: MIT
License-File: LICENSE
Classifier: Development Status :: 3 - Alpha
Classifier: Intended Audience :: Developers
Classifier: Intended Audience :: Science/Research
Classifier: Topic :: Internet
Classifier: Topic :: Scientific/Engineering
Classifier: Topic :: Software Development :: Libraries :: Python Modules
Classifier: Topic :: System
Classifier: Topic :: System :: Distributed Computing
Classifier: Topic :: System :: Networking
Classifier: Topic :: Utilities
Classifier: Programming Language :: Python :: 3 :: Only
Classifier: Programming Language :: Python :: 3
Classifier: Programming Language :: Python :: 3.10
Classifier: Programming Language :: Python :: 3.11
Classifier: Programming Language :: Python :: 3.12
Classifier: Programming Language :: Python :: 3.13
Classifier: License :: OSI Approved :: MIT License
Classifier: Natural Language :: English
Classifier: Typing :: Typed
Requires-Dist: loguru>=0.7.3
Requires-Python: >=3.10
Project-URL: Documentation, https://jacklowrie.github.io/chordnet/chordnet.html
Project-URL: History, https://github.com/jacklowrie/chordnet/releases
Project-URL: Homepage, https://github.com/jacklowrie/chordnet
Project-URL: Issues, https://github.com/jacklowrie/chordnet/issues
Project-URL: PyPI, https://pypi.org/project/chordnet/
Project-URL: Source, https://github.com/jacklowrie/chordnet
Project-URL: download, https://github.com/jacklowrie/chordnet/releases
